pypackaging/__init__.py
pypackaging/cli.py
pypackaging/pypackaging.py
pypackaging-0.1.0.dist-info/AUTHORS.rst
pypackaging-0.1.0.dist-info/LICENSE
pypackaging-0.1.0.dist-info/METADATA
pypackaging-0.1.0.dist-info/WHEEL
pypackaging-0.1.0.dist-info/entry_points.txt
pypackaging-0.1.0.dist-info/top_level.txt
pypackaging-0.1.0.dist-info/RECORD
